{
  "title": "Galio",
  "associatedMaps": [],
  "associatedChampions": [
    3
  ],
  "_notes": "https://www.mobafire.com/league-of-legends/build/sanuns-diamond-galio-guide-top-amp-mid-544388",
  "_author": "sanun",
  "blocks": [
    {
      "type": "Starting Items",
      "items": [
        {
          "id": "1056",
          "count": 1
        },
        {
          "id": "2003",
          "count": 1
        },
        {
          "id": "1054",
          "count": 1
        },
        {
          "id": "1082",
          "count": 1
        }
      ]
    },
    {
      "type": "Early Buys",
      "items": [
        {
          "id": "1001",
          "count": 1
        },
        {
          "id": "3067",
          "count": 1
        }
      ]
    },
    {
      "type": "Boots",
      "items": [
        {
          "id": "3020",
          "count": 1
        },
        {
          "id": "3111",
          "count": 1
        }
      ]
    },
    {
      "type": "Core Item",
      "items": [
        {
          "id": "3152",
          "count": 1
        }
      ]
    },
    {
      "type": "Good options",
      "items": [
        {
          "id": "3165",
          "count": 1
        },
        {
          "id": "3157",
          "count": 1
        },
        {
          "id": "3089",
          "count": 1
        },
        {
          "id": "6655",
          "count": 1
        },
        {
          "id": "3135",
          "count": 1
        },
        {
          "id": "3041",
          "count": 1
        }
      ]
    },
    {
      "type": "Full Build Example",
      "items": [
        {
          "id": "3152",
          "count": 1
        },
        {
          "id": "3020",
          "count": 1
        },
        {
          "id": "3165",
          "count": 1
        },
        {
          "id": "3157",
          "count": 1
        },
        {
          "id": "3089",
          "count": 1
        },
        {
          "id": "3135",
          "count": 1
        }
      ]
    }
  ]
}